ethercheck/__init__.py
ethercheck/ethercheck.py
ethercheck/configs/GOERLI-stable.json
ethercheck/configs/KOVAN-stable.json
ethercheck/configs/MAIN-stable.json
ethercheck/configs/RINKEBY-stable.json
ethercheck/configs/ROPSTEN-stable.json
ethercheck/configs/__init__.py
ethercheck/enums/__init__.py
ethercheck/enums/actions_enum.py
ethercheck/enums/fields_enum.py
ethercheck/enums/modules_enum.py
ethercheck/enums/tags_enum.py
ethercheck/modules/__init__.py
ethercheck/modules/accounts.py
ethercheck/modules/blocks.py
ethercheck/modules/contracts.py
ethercheck/modules/gastracker.py
ethercheck/modules/pro.py
ethercheck/modules/proxy.py
ethercheck/modules/stats.py
ethercheck/modules/tokens.py
ethercheck/modules/transactions.py
ethercheck/utils/__init__.py
ethercheck/utils/conversions.py
ethercheck/utils/parsing.py
ethercheck-1.1.2.dist-info/METADATA
ethercheck-1.1.2.dist-info/WHEEL
ethercheck-1.1.2.dist-info/top_level.txt
ethercheck-1.1.2.dist-info/RECORD
